{
  "agendaItem": [
    {
      "consultation": "https://web1.karlsruhe.de/oparl/bodies/0001/consultations/33593",
      "created": "2025-01-22T10:36:36+01:00",
      "id": "https://web1.karlsruhe.de/oparl/bodies/0001/agendaitems/92115",
      "meeting": "https://web1.karlsruhe.de/oparl/bodies/0001/meetings/10023",
      "modified": "2025-03-03T13:33:42+01:00",
      "name": "Zusammensetzung des Ortschaftsrats Durlach",
      "number": "1",
      "order": 1,
      "public": true,
      "type": "https://schema.oparl.org/1.1/AgendaItem"
    },
    {
      "created": "2025-01-20T10:43:27+01:00",
      "id": "https://web1.karlsruhe.de/oparl/bodies/0001/agendaitems/92043",
      "meeting": "https://web1.karlsruhe.de/oparl/bodies/0001/meetings/10023",
      "modified": "2025-03-03T13:33:42+01:00",
      "name": "Ausscheiden von Herrn David Willimzig aus dem Ortschaftsrat",
      "number": "1.1",
      "order": 2,
      "public": true,
      "result": "einstimmig beschlossen",
      "type": "https://schema.oparl.org/1.1/AgendaItem"
    },
    {
      "created": "2025-01-20T10:43:57+01:00",
      "id": "https://web1.karlsruhe.de/oparl/bodies/0001/agendaitems/92044",
      "meeting": "https://web1.karlsruhe.de/oparl/bodies/0001/meetings/10023",
      "modified": "2025-03-03T13:33:42+01:00",
      "name": "Feststellung des Nichtvorliegens von Hinderungsgründen bei der nachrückenden Ersatzperson Herrn Achim Kluger",
      "number": "1.2",
      "order": 3,
      "public": true,
      "result": "einstimmig beschlossen",
      "type": "https://schema.oparl.org/1.1/AgendaItem"
    },
    {
      "created": "2025-01-20T10:44:09+01:00",
      "id": "https://web1.karlsruhe.de/oparl/bodies/0001/agendaitems/92045",
      "meeting": "https://web1.karlsruhe.de/oparl/bodies/0001/meetings/10023",
      "modified": "2025-03-03T13:33:42+01:00",
      "name": "Verpflichtung des Ortschaftsrats Herrn Achim Kluger",
      "number": "1.3",
      "order": 4,
      "public": true,
      "result": "erledigt",
      "type": "https://schema.oparl.org/1.1/AgendaItem"
    },
    {
      "consultation": "https://web1.karlsruhe.de/oparl/bodies/0001/consultations/33594",
      "created": "2025-01-22T10:36:54+01:00",
      "id": "https://web1.karlsruhe.de/oparl/bodies/0001/agendaitems/92116",
      "meeting": "https://web1.karlsruhe.de/oparl/bodies/0001/meetings/10023",
      "modified": "2025-03-03T13:33:42+01:00",
      "name": "Umbesetzung des Ausschusses für Planung, Bauwesen und Umwelt (Ausschuss II)",
      "number": "1.4",
      "order": 5,
      "public": true,
      "result": "einstimmig beschlossen",
      "type": "https://schema.oparl.org/1.1/AgendaItem"
    },
    {
      "consultation": "https://web1.karlsruhe.de/oparl/bodies/0001/consultations/33595",
      "created": "2025-01-22T10:36:54+01:00",
      "id": "https://web1.karlsruhe.de/oparl/bodies/0001/agendaitems/92117",
      "meeting": "https://web1.karlsruhe.de/oparl/bodies/0001/meetings/10023",
      "modified": "2025-03-03T13:33:42+01:00",
      "name": "Umbesetzung des Kulturbeirats Durlach",
      "number": "1.5",
      "order": 6,
      "public": true,
      "result": "einstimmig beschlossen",
      "type": "https://schema.oparl.org/1.1/AgendaItem"
    },
    {
      "auxiliaryFile": [
        {
          "accessUrl": "https://web1.karlsruhe.de/oparl/bodies/0001/downloadfiles/a/00664895.pdf",
          "created": "2025-02-12T14:11:57+01:00",
          "date": "2025-02-12",
          "downloadUrl": "https://web1.karlsruhe.de/oparl/bodies/0001/downloadfiles/00664895.pdf",
          "fileName": "00664895.pdf",
          "id": "https://web1.karlsruhe.de/oparl/bodies/0001/files/664895",
          "mimeType": "application/pdf",
          "modified": "2025-03-25T10:25:56+01:00",
          "name": "TOP 2 - Präsentation Vorstellung Projekt Glasfaserausbau",
          "type": "https://schema.oparl.org/1.1/File"
        }
      ],
      "created": "2025-01-09T13:35:19+01:00",
      "id": "https://web1.karlsruhe.de/oparl/bodies/0001/agendaitems/91875",
      "meeting": "https://web1.karlsruhe.de/oparl/bodies/0001/meetings/10023",
      "modified": "2025-03-03T13:33:42+01:00",
      "name": "Vorstellung Projekt Glasfaserausbau Untermühl, Dornwald und Aue",
      "number": "2",
      "order": 7,
      "public": true,
      "result": "Kenntnisnahme",
      "type": "https://schema.oparl.org/1.1/AgendaItem"
    },
    {
      "auxiliaryFile": [
        {
          "accessUrl": "https://web1.karlsruhe.de/oparl/bodies/0001/downloadfiles/a/00664893.pdf",
          "created": "2025-02-12T14:11:34+01:00",
          "date": "2025-02-12",
          "downloadUrl": "https://web1.karlsruhe.de/oparl/bodies/0001/downloadfiles/00664893.pdf",
          "fileName": "00664893.pdf",
          "id": "https://web1.karlsruhe.de/oparl/bodies/0001/files/664893",
          "mimeType": "application/pdf",
          "modified": "2025-03-25T10:25:56+01:00",
          "name": "TOP 3 Jährlicher Bericht der Abt. HGW",
          "type": "https://schema.oparl.org/1.1/File"
        }
      ],
      "created": "2024-10-23T14:27:17+02:00",
      "id": "https://web1.karlsruhe.de/oparl/bodies/0001/agendaitems/90840",
      "meeting": "https://web1.karlsruhe.de/oparl/bodies/0001/meetings/10023",
      "modified": "2025-03-03T13:33:42+01:00",
      "name": "Jährlicher Bericht der Abteilung Hochbau und Gebäudewirtschaft Durlach",
      "number": "3",
      "order": 8,
      "public": true,
      "result": "Kenntnisnahme",
      "type": "https://schema.oparl.org/1.1/AgendaItem"
    },
    {
      "consultation": "https://web1.karlsruhe.de/oparl/bodies/0001/consultations/33526",
      "created": "2025-01-22T10:38:52+01:00",
      "id": "https://web1.karlsruhe.de/oparl/bodies/0001/agendaitems/92118",
      "meeting": "https://web1.karlsruhe.de/oparl/bodies/0001/meetings/10023",
      "modified": "2025-03-03T13:33:42+01:00",
      "name": "Kultursommer 2025",
      "number": "4",
      "order": 9,
      "public": true,
      "result": "einstimmig beschlossen",
      "type": "https://schema.oparl.org/1.1/AgendaItem"
    },
    {
      "consultation": "https://web1.karlsruhe.de/oparl/bodies/0001/consultations/33420",
      "created": "2025-01-07T16:09:42+01:00",
      "id": "https://web1.karlsruhe.de/oparl/bodies/0001/agendaitems/91829",
      "meeting": "https://web1.karlsruhe.de/oparl/bodies/0001/meetings/10023",
      "modified": "2025-03-03T13:33:42+01:00",
      "name": "Errichtung von Feinstaub-Messstationen zur Stärkung der Gesundheit in Durlach",
      "number": "5",
      "order": 10,
      "public": true,
      "result": "erledigt",
      "type": "https://schema.oparl.org/1.1/AgendaItem"
    },
    {
      "consultation": "https://web1.karlsruhe.de/oparl/bodies/0001/consultations/33458",
      "created": "2025-01-07T16:09:42+01:00",
      "id": "https://web1.karlsruhe.de/oparl/bodies/0001/agendaitems/91830",
      "meeting": "https://web1.karlsruhe.de/oparl/bodies/0001/meetings/10023",
      "modified": "2025-03-03T13:33:42+01:00",
      "name": "Verlegung der Haltestelle für den Schulbus von der Weiherstraße in den Weiherhof",
      "number": "6",
      "order": 11,
      "public": true,
      "result": "verwiesen in Fachausschuss",
      "type": "https://schema.oparl.org/1.1/AgendaItem"
    },
    {
      "consultation": "https://web1.karlsruhe.de/oparl/bodies/0001/consultations/33477",
      "created": "2025-01-07T16:09:42+01:00",
      "id": "https://web1.karlsruhe.de/oparl/bodies/0001/agendaitems/91831",
      "meeting": "https://web1.karlsruhe.de/oparl/bodies/0001/meetings/10023",
      "modified": "2025-03-03T13:33:42+01:00",
      "name": "Zustand der Durlacher Brücken",
      "number": "7",
      "order": 12,
      "public": true,
      "result": "Kenntnisnahme",
      "type": "https://schema.oparl.org/1.1/AgendaItem"
    },
    {
      "consultation": "https://web1.karlsruhe.de/oparl/bodies/0001/consultations/33486",
      "created": "2025-01-07T16:09:42+01:00",
      "id": "https://web1.karlsruhe.de/oparl/bodies/0001/agendaitems/91832",
      "meeting": "https://web1.karlsruhe.de/oparl/bodies/0001/meetings/10023",
      "modified": "2025-03-03T13:33:42+01:00",
      "name": "Erneuerung des Treppenwegs zum Turmberg",
      "number": "8",
      "order": 13,
      "public": true,
      "result": "verwiesen in Fachausschuss",
      "type": "https://schema.oparl.org/1.1/AgendaItem"
    },
    {
      "created": "2025-01-07T16:10:01+01:00",
      "id": "https://web1.karlsruhe.de/oparl/bodies/0001/agendaitems/91833",
      "meeting": "https://web1.karlsruhe.de/oparl/bodies/0001/meetings/10023",
      "modified": "2025-03-03T13:33:42+01:00",
      "name": "Mitteilungen des Stadtamtes Durlach",
      "number": "9",
      "order": 14,
      "public": true,
      "type": "https://schema.oparl.org/1.1/AgendaItem"
    },
    {
      "created": "2025-01-07T16:10:09+01:00",
      "id": "https://web1.karlsruhe.de/oparl/bodies/0001/agendaitems/91834",
      "meeting": "https://web1.karlsruhe.de/oparl/bodies/0001/meetings/10023",
      "modified": "2025-03-03T13:33:42+01:00",
      "name": "Mündliche Fragen",
      "number": "10",
      "order": 15,
      "public": true,
      "type": "https://schema.oparl.org/1.1/AgendaItem"
    }
  ],
  "auxiliaryFile": [
    {
      "accessUrl": "https://web1.karlsruhe.de/oparl/bodies/0001/downloadfiles/a/00665262.pdf",
      "created": "2025-02-27T14:39:13+01:00",
      "date": "2025-02-27",
      "downloadUrl": "https://web1.karlsruhe.de/oparl/bodies/0001/downloadfiles/00665262.pdf",
      "fileName": "00665262.pdf",
      "id": "https://web1.karlsruhe.de/oparl/bodies/0001/files/665262",
      "mimeType": "application/pdf",
      "modified": "2025-03-25T10:26:02+01:00",
      "name": "Protokoll OR 12.02.2025",
      "type": "https://schema.oparl.org/1.1/File"
    }
  ],
  "created": "2024-10-11T17:52:44+02:00",
  "end": "2025-02-12T00:00:00+01:00",
  "id": "https://web1.karlsruhe.de/oparl/bodies/0001/meetings/10023",
  "invitation": {
    "accessUrl": "https://web1.karlsruhe.de/oparl/bodies/0001/downloadfiles/a/00664558.pdf",
    "created": "2025-01-29T10:31:10+01:00",
    "date": "2025-01-29",
    "downloadUrl": "https://web1.karlsruhe.de/oparl/bodies/0001/downloadfiles/00664558.pdf",
    "fileName": "00664558.pdf",
    "id": "https://web1.karlsruhe.de/oparl/bodies/0001/files/664558",
    "mimeType": "application/pdf",
    "modified": "2025-03-03T14:30:18+01:00",
    "name": "Tagesordnung OR 12.02.2025",
    "type": "https://schema.oparl.org/1.1/File"
  },
  "location": {
    "created": "2024-10-11T17:52:44+02:00",
    "description": "Bürgersaal im Rathaus, Pfinztalstr. 33",
    "id": "https://web1.karlsruhe.de/oparl/bodies/0001/locations/si/10023",
    "modified": "2025-03-25T10:25:55+01:00",
    "type": "https://schema.oparl.org/1.1/Location"
  },
  "modified": "2025-03-25T10:25:55+01:00",
  "name": "Ortschaftsrat Durlach (öffentlich/nicht öffentlich)",
  "organization": [
    "https://web1.karlsruhe.de/oparl/bodies/0001/organizations/gr/40333"
  ],
  "start": "2025-02-12T17:00:00+01:00",
  "type": "https://schema.oparl.org/1.1/Meeting"
}
