{
  "agendaItem": [
    {
      "consultation": "https://web1.karlsruhe.de/oparl/bodies/0001/consultations/2393",
      "created": "2016-10-12T09:08:40+02:00",
      "id": "https://web1.karlsruhe.de/oparl/bodies/0001/agendaitems/17206",
      "meeting": "https://web1.karlsruhe.de/oparl/bodies/0001/meetings/1284",
      "modified": "2025-03-03T13:33:42+01:00",
      "name": "Zusammensetzung des Gemeinderates: Ausscheiden der Stadträtin Dr. Hildegund Brandenburg und Nachrücken der Frau Ute Schulze-Harzer",
      "number": "2",
      "order": 1208,
      "public": true,
      "type": "https://schema.oparl.org/1.1/AgendaItem"
    },
    {
      "consultation": "https://web1.karlsruhe.de/oparl/bodies/0001/consultations/2352",
      "created": "2016-10-12T09:08:40+02:00",
      "id": "https://web1.karlsruhe.de/oparl/bodies/0001/agendaitems/17165",
      "meeting": "https://web1.karlsruhe.de/oparl/bodies/0001/meetings/1284",
      "modified": "2025-03-03T13:33:42+01:00",
      "name": "Wahl eines Mitglieds des Gemeinderates zur Verpflichtung des Oberbürgermeister",
      "number": "3",
      "order": 2215,
      "public": true,
      "type": "https://schema.oparl.org/1.1/AgendaItem"
    },
    {
      "consultation": "https://web1.karlsruhe.de/oparl/bodies/0001/consultations/2353",
      "created": "2016-10-12T09:08:40+02:00",
      "id": "https://web1.karlsruhe.de/oparl/bodies/0001/agendaitems/17166",
      "meeting": "https://web1.karlsruhe.de/oparl/bodies/0001/meetings/1284",
      "modified": "2025-03-03T13:33:42+01:00",
      "name": "Erweiterung des  Hanne-Landgraf-Hauses in Karlsruhe-Grötzingen: Besetzung des Vermittlungsausschusses",
      "number": "4",
      "order": 3114,
      "public": true,
      "type": "https://schema.oparl.org/1.1/AgendaItem"
    },
    {
      "consultation": "https://web1.karlsruhe.de/oparl/bodies/0001/consultations/2354",
      "created": "2016-10-12T09:08:40+02:00",
      "id": "https://web1.karlsruhe.de/oparl/bodies/0001/agendaitems/17167",
      "meeting": "https://web1.karlsruhe.de/oparl/bodies/0001/meetings/1284",
      "modified": "2025-03-03T13:33:42+01:00",
      "name": "Sanierungsgebiet \"SEP City-West\": Bildung eines Sanierungsbeirates",
      "number": "5",
      "order": 3857,
      "public": true,
      "type": "https://schema.oparl.org/1.1/AgendaItem"
    },
    {
      "consultation": "https://web1.karlsruhe.de/oparl/bodies/0001/consultations/2355",
      "created": "2016-10-12T09:08:40+02:00",
      "id": "https://web1.karlsruhe.de/oparl/bodies/0001/agendaitems/17168",
      "meeting": "https://web1.karlsruhe.de/oparl/bodies/0001/meetings/1284",
      "modified": "2025-03-03T13:33:42+01:00",
      "name": "Umbesetzung gemeinderätlicher Ausschüsse und Gremien a) Änderung infolge Ausscheidens Frau Dr. Splett aus dem Gemeinderat b) Änderung infolge Ausscheidens sachverständiger Einwohner",
      "number": "6",
      "order": 4543,
      "public": true,
      "type": "https://schema.oparl.org/1.1/AgendaItem"
    },
    {
      "consultation": "https://web1.karlsruhe.de/oparl/bodies/0001/consultations/2356",
      "created": "2016-10-12T09:08:40+02:00",
      "id": "https://web1.karlsruhe.de/oparl/bodies/0001/agendaitems/17169",
      "meeting": "https://web1.karlsruhe.de/oparl/bodies/0001/meetings/1284",
      "modified": "2025-03-03T13:33:42+01:00",
      "name": "Zukunft des Wildparkstadions: a) Aufhebung der Beschlüsse des Gemeinderates vom 23.05.2006 und 25.07.2006 b) Beschluss zur weiteren Vorgehensweise",
      "number": "7",
      "order": 5103,
      "public": true,
      "type": "https://schema.oparl.org/1.1/AgendaItem"
    },
    {
      "consultation": "https://web1.karlsruhe.de/oparl/bodies/0001/consultations/2357",
      "created": "2016-10-12T09:08:40+02:00",
      "id": "https://web1.karlsruhe.de/oparl/bodies/0001/agendaitems/17170",
      "meeting": "https://web1.karlsruhe.de/oparl/bodies/0001/meetings/1284",
      "modified": "2025-03-03T13:33:42+01:00",
      "name": "Geltendmachung bürgerlich-rechtlicher Unterhaltsansprüche gegen Eltern behinderter Kinder in Werkstätten und Förder- und Betreuungsgruppen",
      "number": "8",
      "order": 5582,
      "public": true,
      "type": "https://schema.oparl.org/1.1/AgendaItem"
    },
    {
      "consultation": "https://web1.karlsruhe.de/oparl/bodies/0001/consultations/2358",
      "created": "2016-10-12T09:08:40+02:00",
      "id": "https://web1.karlsruhe.de/oparl/bodies/0001/agendaitems/17171",
      "meeting": "https://web1.karlsruhe.de/oparl/bodies/0001/meetings/1284",
      "modified": "2025-03-03T13:33:42+01:00",
      "name": "Eingliederungshilfe für Menschen mit Behinderungen: Jahresbilanz 2005",
      "number": "9",
      "order": 6046,
      "public": true,
      "type": "https://schema.oparl.org/1.1/AgendaItem"
    },
    {
      "consultation": "https://web1.karlsruhe.de/oparl/bodies/0001/consultations/2360",
      "created": "2016-10-12T09:08:40+02:00",
      "id": "https://web1.karlsruhe.de/oparl/bodies/0001/agendaitems/17173",
      "meeting": "https://web1.karlsruhe.de/oparl/bodies/0001/meetings/1284",
      "modified": "2025-03-03T13:33:42+01:00",
      "name": "Benennung der Straßen im Konversionsgebiet Neureut",
      "number": "11",
      "order": 6985,
      "public": true,
      "type": "https://schema.oparl.org/1.1/AgendaItem"
    },
    {
      "consultation": "https://web1.karlsruhe.de/oparl/bodies/0001/consultations/2362",
      "created": "2016-10-12T09:08:40+02:00",
      "id": "https://web1.karlsruhe.de/oparl/bodies/0001/agendaitems/17175",
      "meeting": "https://web1.karlsruhe.de/oparl/bodies/0001/meetings/1284",
      "modified": "2025-03-03T13:33:42+01:00",
      "name": "Antrag CDU: Kleingartenanlage in der Stuttgarter Straße",
      "number": "13.1",
      "order": 7719,
      "public": true,
      "type": "https://schema.oparl.org/1.1/AgendaItem"
    },
    {
      "consultation": "https://web1.karlsruhe.de/oparl/bodies/0001/consultations/2363",
      "created": "2016-10-12T09:08:40+02:00",
      "id": "https://web1.karlsruhe.de/oparl/bodies/0001/agendaitems/17176",
      "meeting": "https://web1.karlsruhe.de/oparl/bodies/0001/meetings/1284",
      "modified": "2025-03-03T13:33:42+01:00",
      "name": "Antrag SPD: Kleingartenanlage in der Stuttgarter Straße",
      "number": "13.2",
      "order": 7723,
      "public": true,
      "type": "https://schema.oparl.org/1.1/AgendaItem"
    },
    {
      "consultation": "https://web1.karlsruhe.de/oparl/bodies/0001/consultations/2364",
      "created": "2016-10-12T09:08:40+02:00",
      "id": "https://web1.karlsruhe.de/oparl/bodies/0001/agendaitems/17177",
      "meeting": "https://web1.karlsruhe.de/oparl/bodies/0001/meetings/1284",
      "modified": "2025-03-03T13:33:42+01:00",
      "name": "Antrag CDU: Jugendhilfeplanung nach § 80 SGB VIII",
      "number": "14",
      "order": 7782,
      "public": true,
      "type": "https://schema.oparl.org/1.1/AgendaItem"
    },
    {
      "consultation": "https://web1.karlsruhe.de/oparl/bodies/0001/consultations/2365",
      "created": "2016-10-12T09:08:40+02:00",
      "id": "https://web1.karlsruhe.de/oparl/bodies/0001/agendaitems/17178",
      "meeting": "https://web1.karlsruhe.de/oparl/bodies/0001/meetings/1284",
      "modified": "2025-03-03T13:33:42+01:00",
      "name": "Antrag CDU: Umwegrentabilität",
      "number": "15",
      "order": 8012,
      "public": true,
      "type": "https://schema.oparl.org/1.1/AgendaItem"
    },
    {
      "consultation": "https://web1.karlsruhe.de/oparl/bodies/0001/consultations/2366",
      "created": "2016-10-12T09:08:40+02:00",
      "id": "https://web1.karlsruhe.de/oparl/bodies/0001/agendaitems/17179",
      "meeting": "https://web1.karlsruhe.de/oparl/bodies/0001/meetings/1284",
      "modified": "2025-03-03T13:33:42+01:00",
      "name": "Antrag GRÜNE: Naturschutzgebiet \"Alter Flugplatz\"",
      "number": "16",
      "order": 8209,
      "public": true,
      "type": "https://schema.oparl.org/1.1/AgendaItem"
    },
    {
      "consultation": "https://web1.karlsruhe.de/oparl/bodies/0001/consultations/2367",
      "created": "2016-10-12T09:08:40+02:00",
      "id": "https://web1.karlsruhe.de/oparl/bodies/0001/agendaitems/17180",
      "meeting": "https://web1.karlsruhe.de/oparl/bodies/0001/meetings/1284",
      "modified": "2025-03-03T13:33:42+01:00",
      "name": "Antrag SPD: Erwerb Gebäude und Grundstück Kriegsstraße 103 (ehemaliges Versorgungsamt)",
      "number": "17",
      "order": 8378,
      "public": true,
      "type": "https://schema.oparl.org/1.1/AgendaItem"
    },
    {
      "consultation": "https://web1.karlsruhe.de/oparl/bodies/0001/consultations/2368",
      "created": "2016-10-12T09:08:40+02:00",
      "id": "https://web1.karlsruhe.de/oparl/bodies/0001/agendaitems/17181",
      "meeting": "https://web1.karlsruhe.de/oparl/bodies/0001/meetings/1284",
      "modified": "2025-03-03T13:33:42+01:00",
      "name": "Antrag GRÜNE: Entwidmung öffentlicher Stellplätze zugunsten von Car-Sharing",
      "number": "18",
      "order": 8546,
      "public": true,
      "type": "https://schema.oparl.org/1.1/AgendaItem"
    },
    {
      "consultation": "https://web1.karlsruhe.de/oparl/bodies/0001/consultations/2369",
      "created": "2016-10-12T09:08:40+02:00",
      "id": "https://web1.karlsruhe.de/oparl/bodies/0001/agendaitems/17182",
      "meeting": "https://web1.karlsruhe.de/oparl/bodies/0001/meetings/1284",
      "modified": "2025-03-03T13:33:42+01:00",
      "name": "Antrag SPD: Kinderpass für Asylbewerber",
      "number": "19",
      "order": 8695,
      "public": true,
      "type": "https://schema.oparl.org/1.1/AgendaItem"
    },
    {
      "consultation": "https://web1.karlsruhe.de/oparl/bodies/0001/consultations/2370",
      "created": "2016-10-12T09:08:40+02:00",
      "id": "https://web1.karlsruhe.de/oparl/bodies/0001/agendaitems/17183",
      "meeting": "https://web1.karlsruhe.de/oparl/bodies/0001/meetings/1284",
      "modified": "2025-03-03T13:33:42+01:00",
      "name": "Antrag GRÜNE: Spielzonen in verkehrsberuhigten Bereichen",
      "number": "20",
      "order": 9013,
      "public": true,
      "type": "https://schema.oparl.org/1.1/AgendaItem"
    },
    {
      "consultation": "https://web1.karlsruhe.de/oparl/bodies/0001/consultations/2371",
      "created": "2016-10-12T09:08:40+02:00",
      "id": "https://web1.karlsruhe.de/oparl/bodies/0001/agendaitems/17184",
      "meeting": "https://web1.karlsruhe.de/oparl/bodies/0001/meetings/1284",
      "modified": "2025-03-03T13:33:42+01:00",
      "name": "Antrag SPD: Konzept \"Proaktive Arbeitsplatzsuche\"",
      "number": "21",
      "order": 9150,
      "public": true,
      "type": "https://schema.oparl.org/1.1/AgendaItem"
    },
    {
      "consultation": "https://web1.karlsruhe.de/oparl/bodies/0001/consultations/2372",
      "created": "2016-10-12T09:08:40+02:00",
      "id": "https://web1.karlsruhe.de/oparl/bodies/0001/agendaitems/17185",
      "meeting": "https://web1.karlsruhe.de/oparl/bodies/0001/meetings/1284",
      "modified": "2025-03-03T13:33:42+01:00",
      "name": "Antrag GRÜNE: Soziale Staffelung der Elternbeiträge für Kindertageseinrichtungen",
      "number": "22",
      "order": 9256,
      "public": true,
      "type": "https://schema.oparl.org/1.1/AgendaItem"
    },
    {
      "consultation": "https://web1.karlsruhe.de/oparl/bodies/0001/consultations/2373",
      "created": "2016-10-12T09:08:40+02:00",
      "id": "https://web1.karlsruhe.de/oparl/bodies/0001/agendaitems/17186",
      "meeting": "https://web1.karlsruhe.de/oparl/bodies/0001/meetings/1284",
      "modified": "2025-03-03T13:33:42+01:00",
      "name": "Anfrage FDP/Aufbruch: Bericht über die Aktivitäten mit den verschiedenen Partnerstädten",
      "number": "23",
      "order": 9361,
      "public": true,
      "type": "https://schema.oparl.org/1.1/AgendaItem"
    },
    {
      "consultation": "https://web1.karlsruhe.de/oparl/bodies/0001/consultations/2374",
      "created": "2016-10-12T09:08:40+02:00",
      "id": "https://web1.karlsruhe.de/oparl/bodies/0001/agendaitems/17187",
      "meeting": "https://web1.karlsruhe.de/oparl/bodies/0001/meetings/1284",
      "modified": "2025-03-03T13:33:42+01:00",
      "name": "Anfrage GRÜNE: Geplante Modernisierung  des Instituts für Transurane",
      "number": "24",
      "order": 9453,
      "public": true,
      "type": "https://schema.oparl.org/1.1/AgendaItem"
    },
    {
      "consultation": "https://web1.karlsruhe.de/oparl/bodies/0001/consultations/2375",
      "created": "2016-10-12T09:08:40+02:00",
      "id": "https://web1.karlsruhe.de/oparl/bodies/0001/agendaitems/17188",
      "meeting": "https://web1.karlsruhe.de/oparl/bodies/0001/meetings/1284",
      "modified": "2025-03-03T13:33:42+01:00",
      "name": "Anfrage GRÜNE: Nichtöffentlichkeit von Ausschusssitzungen",
      "number": "25",
      "order": 9536,
      "public": true,
      "type": "https://schema.oparl.org/1.1/AgendaItem"
    },
    {
      "consultation": "https://web1.karlsruhe.de/oparl/bodies/0001/consultations/2376",
      "created": "2016-10-12T09:08:40+02:00",
      "id": "https://web1.karlsruhe.de/oparl/bodies/0001/agendaitems/17189",
      "meeting": "https://web1.karlsruhe.de/oparl/bodies/0001/meetings/1284",
      "modified": "2025-03-03T13:33:42+01:00",
      "name": "Anfrage CDU: Jüdische Friedhöfe in Karlsruhe",
      "number": "26",
      "order": 9608,
      "public": true,
      "type": "https://schema.oparl.org/1.1/AgendaItem"
    },
    {
      "consultation": "https://web1.karlsruhe.de/oparl/bodies/0001/consultations/2377",
      "created": "2016-10-12T09:08:40+02:00",
      "id": "https://web1.karlsruhe.de/oparl/bodies/0001/agendaitems/17190",
      "meeting": "https://web1.karlsruhe.de/oparl/bodies/0001/meetings/1284",
      "modified": "2025-03-03T13:33:42+01:00",
      "name": "Anfrage CDU: Fachpersonalmangel im akademischen/wissenschaftlichen Bereich",
      "number": "27",
      "order": 9680,
      "public": true,
      "type": "https://schema.oparl.org/1.1/AgendaItem"
    },
    {
      "consultation": "https://web1.karlsruhe.de/oparl/bodies/0001/consultations/2378",
      "created": "2016-10-12T09:08:40+02:00",
      "id": "https://web1.karlsruhe.de/oparl/bodies/0001/agendaitems/17191",
      "meeting": "https://web1.karlsruhe.de/oparl/bodies/0001/meetings/1284",
      "modified": "2025-03-03T13:33:42+01:00",
      "name": "Anfrage SPD: Ausbildungssituation bei der Stadt Karlsruhe",
      "number": "28",
      "order": 9738,
      "public": true,
      "type": "https://schema.oparl.org/1.1/AgendaItem"
    },
    {
      "consultation": "https://web1.karlsruhe.de/oparl/bodies/0001/consultations/2379",
      "created": "2016-10-12T09:08:40+02:00",
      "id": "https://web1.karlsruhe.de/oparl/bodies/0001/agendaitems/17192",
      "meeting": "https://web1.karlsruhe.de/oparl/bodies/0001/meetings/1284",
      "modified": "2025-03-03T13:33:42+01:00",
      "name": "Anfrage SPD: Schließung der Eislaufhalle Neureut - alternative Trainingsmöglichkeiten für Vereine",
      "number": "29",
      "order": 9796,
      "public": true,
      "type": "https://schema.oparl.org/1.1/AgendaItem"
    },
    {
      "consultation": "https://web1.karlsruhe.de/oparl/bodies/0001/consultations/2380",
      "created": "2016-10-12T09:08:40+02:00",
      "id": "https://web1.karlsruhe.de/oparl/bodies/0001/agendaitems/17193",
      "meeting": "https://web1.karlsruhe.de/oparl/bodies/0001/meetings/1284",
      "modified": "2025-03-03T13:33:42+01:00",
      "name": "Anfrage SPD: Schule in der östlichen Südstadt",
      "number": "30",
      "order": 10007,
      "public": true,
      "type": "https://schema.oparl.org/1.1/AgendaItem"
    },
    {
      "consultation": "https://web1.karlsruhe.de/oparl/bodies/0001/consultations/2381",
      "created": "2016-10-12T09:08:40+02:00",
      "id": "https://web1.karlsruhe.de/oparl/bodies/0001/agendaitems/17194",
      "meeting": "https://web1.karlsruhe.de/oparl/bodies/0001/meetings/1284",
      "modified": "2025-03-03T13:33:42+01:00",
      "name": "Anfrage CDU: Finanzielle Entlastung von Familien",
      "number": "31",
      "order": 10053,
      "public": true,
      "type": "https://schema.oparl.org/1.1/AgendaItem"
    },
    {
      "consultation": "https://web1.karlsruhe.de/oparl/bodies/0001/consultations/2382",
      "created": "2016-10-12T09:08:40+02:00",
      "id": "https://web1.karlsruhe.de/oparl/bodies/0001/agendaitems/17195",
      "meeting": "https://web1.karlsruhe.de/oparl/bodies/0001/meetings/1284",
      "modified": "2025-03-03T13:33:42+01:00",
      "name": "Anfrage SPD: Auswirkungen der Arbeitszeiterhöhung",
      "number": "32",
      "order": 10098,
      "public": true,
      "type": "https://schema.oparl.org/1.1/AgendaItem"
    },
    {
      "consultation": "https://web1.karlsruhe.de/oparl/bodies/0001/consultations/2383",
      "created": "2016-10-12T09:08:40+02:00",
      "id": "https://web1.karlsruhe.de/oparl/bodies/0001/agendaitems/17196",
      "meeting": "https://web1.karlsruhe.de/oparl/bodies/0001/meetings/1284",
      "modified": "2025-03-03T13:33:42+01:00",
      "name": "Anfrage SPD: Betreuung von Zuwanderern bei der Jüdischen Gemeinde Karlsruhe",
      "number": "33",
      "order": 10131,
      "public": true,
      "type": "https://schema.oparl.org/1.1/AgendaItem"
    },
    {
      "consultation": "https://web1.karlsruhe.de/oparl/bodies/0001/consultations/2384",
      "created": "2016-10-12T09:08:40+02:00",
      "id": "https://web1.karlsruhe.de/oparl/bodies/0001/agendaitems/17197",
      "meeting": "https://web1.karlsruhe.de/oparl/bodies/0001/meetings/1284",
      "modified": "2025-03-03T13:33:42+01:00",
      "name": "Anfrage CDU: Kindertageseinrichtungen mit gemeindeübergreifendem Einzugsgebiet",
      "number": "34",
      "order": 10161,
      "public": true,
      "type": "https://schema.oparl.org/1.1/AgendaItem"
    },
    {
      "consultation": "https://web1.karlsruhe.de/oparl/bodies/0001/consultations/2385",
      "created": "2016-10-12T09:08:40+02:00",
      "id": "https://web1.karlsruhe.de/oparl/bodies/0001/agendaitems/17198",
      "meeting": "https://web1.karlsruhe.de/oparl/bodies/0001/meetings/1284",
      "modified": "2025-03-03T13:33:42+01:00",
      "name": "Anfrage SPD: Projekt Wohnraumakquise",
      "number": "35",
      "order": 10187,
      "public": true,
      "type": "https://schema.oparl.org/1.1/AgendaItem"
    },
    {
      "consultation": "https://web1.karlsruhe.de/oparl/bodies/0001/consultations/2386",
      "created": "2016-10-12T09:08:40+02:00",
      "id": "https://web1.karlsruhe.de/oparl/bodies/0001/agendaitems/17199",
      "meeting": "https://web1.karlsruhe.de/oparl/bodies/0001/meetings/1284",
      "modified": "2025-03-03T13:33:42+01:00",
      "name": "Anfrage SPD: Lärmschutz entlang der Südtangente",
      "number": "36",
      "order": 10204,
      "public": true,
      "type": "https://schema.oparl.org/1.1/AgendaItem"
    }
  ],
  "auxiliaryFile": [
    {
      "accessUrl": "https://web1.karlsruhe.de/oparl/bodies/0001/downloadfiles/a/00022304.pdf",
      "created": "2016-10-12T09:08:36+02:00",
      "date": "2013-08-15",
      "downloadUrl": "https://web1.karlsruhe.de/oparl/bodies/0001/downloadfiles/00022304.pdf",
      "fileName": "00022304.pdf",
      "id": "https://web1.karlsruhe.de/oparl/bodies/0001/files/22304",
      "mimeType": "application/pdf",
      "modified": "2025-03-03T14:30:18+01:00",
      "name": "Tagesordnung öffentl.",
      "type": "https://schema.oparl.org/1.1/File"
    }
  ],
  "created": "2016-10-12T09:08:39+02:00",
  "end": "2006-09-26T00:00:00+02:00",
  "id": "https://web1.karlsruhe.de/oparl/bodies/0001/meetings/1284",
  "location": {
    "created": "2016-10-12T09:08:39+02:00",
    "description": "Großer Sitzungssaal",
    "id": "https://web1.karlsruhe.de/oparl/bodies/0001/locations/si/1284",
    "modified": "2025-03-03T13:33:55+01:00",
    "type": "https://schema.oparl.org/1.1/Location"
  },
  "modified": "2025-03-03T13:33:55+01:00",
  "name": "Gemeinderat",
  "organization": [
    "https://web1.karlsruhe.de/oparl/bodies/0001/organizations/gr/32130"
  ],
  "start": "2006-09-26T15:30:00+02:00",
  "type": "https://schema.oparl.org/1.1/Meeting",
  "verbatimProtocol": {
    "accessUrl": "https://web1.karlsruhe.de/oparl/bodies/0001/downloadfiles/a/00500056.pdf",
    "created": "2016-10-12T09:08:36+02:00",
    "date": "2014-09-10",
    "downloadUrl": "https://web1.karlsruhe.de/oparl/bodies/0001/downloadfiles/00500056.pdf",
    "fileName": "00500056.pdf",
    "id": "https://web1.karlsruhe.de/oparl/bodies/0001/files/500056",
    "mimeType": "application/pdf",
    "modified": "2025-03-03T14:30:18+01:00",
    "name": "Protokoll TOP 15: Antrag der Stadträte Wolfram Jäger, Bernhard Weick und Günther Rüssel, der Stadträtin Bettina Meier-Augenstein (CDU) sowie der CDU-Gemeinderatsfraktion vom 24. Juli 2006: Umwegrentabilität",
    "type": "https://schema.oparl.org/1.1/File"
  }
}
