{
  "agendaItem": [
    {
      "created": "2020-01-14T17:22:40+01:00",
      "id": "https://web1.karlsruhe.de/oparl/bodies/0001/agendaitems/49392",
      "meeting": "https://web1.karlsruhe.de/oparl/bodies/0001/meetings/5932",
      "modified": "2025-03-03T13:33:42+01:00",
      "name": "Fragen und Anregungen der Einwohnerinnen und Einwohner",
      "number": "1",
      "order": 1,
      "public": true,
      "type": "https://schema.oparl.org/1.1/AgendaItem"
    },
    {
      "consultation": "https://web1.karlsruhe.de/oparl/bodies/0001/consultations/17671",
      "created": "2020-01-14T17:21:17+01:00",
      "id": "https://web1.karlsruhe.de/oparl/bodies/0001/agendaitems/49381",
      "meeting": "https://web1.karlsruhe.de/oparl/bodies/0001/meetings/5932",
      "modified": "2025-03-03T13:33:42+01:00",
      "name": "Pflegequalität",
      "number": "2",
      "order": 2,
      "public": true,
      "type": "https://schema.oparl.org/1.1/AgendaItem"
    },
    {
      "created": "2020-01-22T16:14:36+01:00",
      "id": "https://web1.karlsruhe.de/oparl/bodies/0001/agendaitems/49592",
      "meeting": "https://web1.karlsruhe.de/oparl/bodies/0001/meetings/5932",
      "modified": "2025-03-03T13:33:42+01:00",
      "name": "Abgesetzt",
      "number": "3",
      "order": 3,
      "public": true,
      "type": "https://schema.oparl.org/1.1/AgendaItem"
    },
    {
      "consultation": "https://web1.karlsruhe.de/oparl/bodies/0001/consultations/17673",
      "created": "2020-01-14T17:21:17+01:00",
      "id": "https://web1.karlsruhe.de/oparl/bodies/0001/agendaitems/49383",
      "meeting": "https://web1.karlsruhe.de/oparl/bodies/0001/meetings/5932",
      "modified": "2025-03-03T13:33:42+01:00",
      "name": "Erschwertes Einfädeln von der Augustenburgstraße in die B10 \"Einfach mal ausprobieren\"",
      "number": "4",
      "order": 4,
      "public": true,
      "type": "https://schema.oparl.org/1.1/AgendaItem"
    },
    {
      "consultation": "https://web1.karlsruhe.de/oparl/bodies/0001/consultations/17674",
      "created": "2020-01-14T17:21:17+01:00",
      "id": "https://web1.karlsruhe.de/oparl/bodies/0001/agendaitems/49384",
      "meeting": "https://web1.karlsruhe.de/oparl/bodies/0001/meetings/5932",
      "modified": "2025-03-03T13:33:42+01:00",
      "name": "Digital Anzeige für Bushaltestellen Bahnhof Grötzingen und Grötzingen Nord",
      "number": "5",
      "order": 5,
      "public": true,
      "type": "https://schema.oparl.org/1.1/AgendaItem"
    },
    {
      "consultation": "https://web1.karlsruhe.de/oparl/bodies/0001/consultations/17675",
      "created": "2020-01-14T17:21:17+01:00",
      "id": "https://web1.karlsruhe.de/oparl/bodies/0001/agendaitems/49385",
      "meeting": "https://web1.karlsruhe.de/oparl/bodies/0001/meetings/5932",
      "modified": "2025-03-03T13:33:42+01:00",
      "name": "Sachstand Bebauungsplanänderung \"Junge Hälden\"",
      "number": "6",
      "order": 6,
      "public": true,
      "type": "https://schema.oparl.org/1.1/AgendaItem"
    },
    {
      "created": "2020-01-22T16:15:03+01:00",
      "id": "https://web1.karlsruhe.de/oparl/bodies/0001/agendaitems/49593",
      "meeting": "https://web1.karlsruhe.de/oparl/bodies/0001/meetings/5932",
      "modified": "2025-03-03T13:33:42+01:00",
      "name": "Abgesetzt",
      "number": "7",
      "order": 7,
      "public": true,
      "type": "https://schema.oparl.org/1.1/AgendaItem"
    },
    {
      "consultation": "https://web1.karlsruhe.de/oparl/bodies/0001/consultations/17677",
      "created": "2020-01-14T17:21:17+01:00",
      "id": "https://web1.karlsruhe.de/oparl/bodies/0001/agendaitems/49387",
      "meeting": "https://web1.karlsruhe.de/oparl/bodies/0001/meetings/5932",
      "modified": "2025-03-03T13:33:42+01:00",
      "name": "Parkplatzmarkierung im Bereich des Bahnhofs Grötzingen",
      "number": "8",
      "order": 8,
      "public": true,
      "type": "https://schema.oparl.org/1.1/AgendaItem"
    },
    {
      "created": "2020-01-14T17:23:18+01:00",
      "id": "https://web1.karlsruhe.de/oparl/bodies/0001/agendaitems/49393",
      "meeting": "https://web1.karlsruhe.de/oparl/bodies/0001/meetings/5932",
      "modified": "2025-03-03T13:33:42+01:00",
      "name": "Bekanntgabe nichtöffentlich gefasster Beschlüsse",
      "number": "9",
      "order": 9,
      "public": true,
      "type": "https://schema.oparl.org/1.1/AgendaItem"
    },
    {
      "consultation": "https://web1.karlsruhe.de/oparl/bodies/0001/consultations/17678",
      "created": "2020-01-14T17:21:17+01:00",
      "id": "https://web1.karlsruhe.de/oparl/bodies/0001/agendaitems/49388",
      "meeting": "https://web1.karlsruhe.de/oparl/bodies/0001/meetings/5932",
      "modified": "2025-03-03T13:33:42+01:00",
      "name": "Bauanträge",
      "number": "10",
      "order": 10,
      "public": true,
      "type": "https://schema.oparl.org/1.1/AgendaItem"
    },
    {
      "created": "2020-01-14T17:23:45+01:00",
      "id": "https://web1.karlsruhe.de/oparl/bodies/0001/agendaitems/49394",
      "meeting": "https://web1.karlsruhe.de/oparl/bodies/0001/meetings/5932",
      "modified": "2025-03-03T13:33:42+01:00",
      "name": "Mitteilungen und Anfragen",
      "number": "11",
      "order": 11,
      "public": true,
      "type": "https://schema.oparl.org/1.1/AgendaItem"
    }
  ],
  "auxiliaryFile": [
    {
      "accessUrl": "https://web1.karlsruhe.de/oparl/bodies/0001/downloadfiles/a/00615000.pdf",
      "created": "2020-02-17T14:06:25+01:00",
      "date": "2020-02-17",
      "downloadUrl": "https://web1.karlsruhe.de/oparl/bodies/0001/downloadfiles/00615000.pdf",
      "fileName": "00615000.pdf",
      "id": "https://web1.karlsruhe.de/oparl/bodies/0001/files/615000",
      "mimeType": "application/pdf",
      "modified": "2025-03-03T14:30:18+01:00",
      "name": "Wortlaut der Beschlüsse der öffentlichen Sitzung des Ortschaftsrates Grötzingen",
      "type": "https://schema.oparl.org/1.1/File"
    },
    {
      "accessUrl": "https://web1.karlsruhe.de/oparl/bodies/0001/downloadfiles/a/00615003.pdf",
      "created": "2020-02-17T14:10:52+01:00",
      "date": "2020-02-17",
      "downloadUrl": "https://web1.karlsruhe.de/oparl/bodies/0001/downloadfiles/00615003.pdf",
      "fileName": "00615003.pdf",
      "id": "https://web1.karlsruhe.de/oparl/bodies/0001/files/615003",
      "mimeType": "application/pdf",
      "modified": "2025-03-03T14:30:18+01:00",
      "name": "20 01 22 Protokoll (ö).OSR",
      "type": "https://schema.oparl.org/1.1/File"
    }
  ],
  "created": "2019-12-03T16:04:11+01:00",
  "end": "2020-01-22T21:00:00+01:00",
  "id": "https://web1.karlsruhe.de/oparl/bodies/0001/meetings/5932",
  "invitation": {
    "accessUrl": "https://web1.karlsruhe.de/oparl/bodies/0001/downloadfiles/a/00614469.pdf",
    "created": "2020-01-23T09:00:16+01:00",
    "date": "2020-01-23",
    "downloadUrl": "https://web1.karlsruhe.de/oparl/bodies/0001/downloadfiles/00614469.pdf",
    "fileName": "00614469.pdf",
    "id": "https://web1.karlsruhe.de/oparl/bodies/0001/files/614469",
    "mimeType": "application/pdf",
    "modified": "2025-03-03T14:30:18+01:00",
    "name": "Tagesordnung Ausschuss/OV (öffentlich)",
    "type": "https://schema.oparl.org/1.1/File"
  },
  "location": {
    "created": "2019-12-03T16:04:11+01:00",
    "description": "Begegnungsstätte, Niddastr. 9",
    "id": "https://web1.karlsruhe.de/oparl/bodies/0001/locations/si/5932",
    "modified": "2025-03-03T13:33:55+01:00",
    "type": "https://schema.oparl.org/1.1/Location"
  },
  "modified": "2025-03-03T13:33:55+01:00",
  "name": "Ortschaftsrat Grötzingen (öffentlich/nicht öffentlich)",
  "organization": [
    "https://web1.karlsruhe.de/oparl/bodies/0001/organizations/gr/33695"
  ],
  "start": "2020-01-22T19:00:00+01:00",
  "type": "https://schema.oparl.org/1.1/Meeting"
}
