{
  "agendaItem": [
    {
      "auxiliaryFile": [
        {
          "accessUrl": "https://web1.karlsruhe.de/oparl/bodies/0001/downloadfiles/a/00662573.pdf",
          "created": "2024-11-08T15:21:21+01:00",
          "date": "2024-11-08",
          "downloadUrl": "https://web1.karlsruhe.de/oparl/bodies/0001/downloadfiles/00662573.pdf",
          "fileName": "00662573.pdf",
          "id": "https://web1.karlsruhe.de/oparl/bodies/0001/files/662573",
          "mimeType": "application/pdf",
          "modified": "2025-04-30T10:38:52+02:00",
          "name": "2024-09-11_TOP_1_Protokollauszug",
          "type": "https://schema.oparl.org/1.1/File"
        }
      ],
      "consultation": "https://web1.karlsruhe.de/oparl/bodies/0001/consultations/32468",
      "created": "2024-09-09T17:06:28+02:00",
      "id": "https://web1.karlsruhe.de/oparl/bodies/0001/agendaitems/89990",
      "meeting": "https://web1.karlsruhe.de/oparl/bodies/0001/meetings/9914",
      "modified": "2025-03-03T13:33:42+01:00",
      "name": "Einführung und Verpflichtung der am 9. Juni 2024 in den Ortschaftsrat gewählten Personen",
      "number": "1",
      "order": 1,
      "public": true,
      "type": "https://schema.oparl.org/1.1/AgendaItem"
    },
    {
      "auxiliaryFile": [
        {
          "accessUrl": "https://web1.karlsruhe.de/oparl/bodies/0001/downloadfiles/a/00662574.pdf",
          "created": "2024-11-08T15:21:32+01:00",
          "date": "2024-11-08",
          "downloadUrl": "https://web1.karlsruhe.de/oparl/bodies/0001/downloadfiles/00662574.pdf",
          "fileName": "00662574.pdf",
          "id": "https://web1.karlsruhe.de/oparl/bodies/0001/files/662574",
          "mimeType": "application/pdf",
          "modified": "2025-04-30T10:38:52+02:00",
          "name": "2024-09-11_TOP_2_Protokollauszug",
          "type": "https://schema.oparl.org/1.1/File"
        }
      ],
      "consultation": "https://web1.karlsruhe.de/oparl/bodies/0001/consultations/32567",
      "created": "2024-09-09T17:06:28+02:00",
      "id": "https://web1.karlsruhe.de/oparl/bodies/0001/agendaitems/89994",
      "meeting": "https://web1.karlsruhe.de/oparl/bodies/0001/meetings/9914",
      "modified": "2025-03-03T13:33:42+01:00",
      "name": "Änderung der Geschäftsordnung",
      "number": "2",
      "order": 2,
      "public": true,
      "type": "https://schema.oparl.org/1.1/AgendaItem"
    },
    {
      "auxiliaryFile": [
        {
          "accessUrl": "https://web1.karlsruhe.de/oparl/bodies/0001/downloadfiles/a/00662575.pdf",
          "created": "2024-11-08T15:21:43+01:00",
          "date": "2024-11-08",
          "downloadUrl": "https://web1.karlsruhe.de/oparl/bodies/0001/downloadfiles/00662575.pdf",
          "fileName": "00662575.pdf",
          "id": "https://web1.karlsruhe.de/oparl/bodies/0001/files/662575",
          "mimeType": "application/pdf",
          "modified": "2025-04-30T10:38:52+02:00",
          "name": "2024-09-11_TOP_3_Protokollauszug",
          "type": "https://schema.oparl.org/1.1/File"
        }
      ],
      "consultation": "https://web1.karlsruhe.de/oparl/bodies/0001/consultations/32569",
      "created": "2024-09-09T17:06:28+02:00",
      "id": "https://web1.karlsruhe.de/oparl/bodies/0001/agendaitems/89995",
      "meeting": "https://web1.karlsruhe.de/oparl/bodies/0001/meetings/9914",
      "modified": "2025-03-03T13:33:42+01:00",
      "name": "Regelungen des Ortschaftsrates Grötzingen in der Legislatur 2024-2029",
      "number": "3",
      "order": 3,
      "public": true,
      "type": "https://schema.oparl.org/1.1/AgendaItem"
    },
    {
      "auxiliaryFile": [
        {
          "accessUrl": "https://web1.karlsruhe.de/oparl/bodies/0001/downloadfiles/a/00662576.pdf",
          "created": "2024-11-08T15:21:54+01:00",
          "date": "2024-11-08",
          "downloadUrl": "https://web1.karlsruhe.de/oparl/bodies/0001/downloadfiles/00662576.pdf",
          "fileName": "00662576.pdf",
          "id": "https://web1.karlsruhe.de/oparl/bodies/0001/files/662576",
          "mimeType": "application/pdf",
          "modified": "2025-04-30T10:38:52+02:00",
          "name": "2024-09-11_TOP_4_Protokollauszug",
          "type": "https://schema.oparl.org/1.1/File"
        }
      ],
      "consultation": "https://web1.karlsruhe.de/oparl/bodies/0001/consultations/32469",
      "created": "2024-09-09T17:06:28+02:00",
      "id": "https://web1.karlsruhe.de/oparl/bodies/0001/agendaitems/89991",
      "meeting": "https://web1.karlsruhe.de/oparl/bodies/0001/meetings/9914",
      "modified": "2025-03-03T13:33:42+01:00",
      "name": "Besetzung von Ausschüssen und Funktionen des Ortschaftsrates",
      "number": "4",
      "order": 4,
      "public": true,
      "type": "https://schema.oparl.org/1.1/AgendaItem"
    },
    {
      "auxiliaryFile": [
        {
          "accessUrl": "https://web1.karlsruhe.de/oparl/bodies/0001/downloadfiles/a/00662577.pdf",
          "created": "2024-11-08T15:22:07+01:00",
          "date": "2024-11-08",
          "downloadUrl": "https://web1.karlsruhe.de/oparl/bodies/0001/downloadfiles/00662577.pdf",
          "fileName": "00662577.pdf",
          "id": "https://web1.karlsruhe.de/oparl/bodies/0001/files/662577",
          "mimeType": "application/pdf",
          "modified": "2025-04-30T10:38:52+02:00",
          "name": "2024-09-11_TOP_5_Protokollauszug",
          "type": "https://schema.oparl.org/1.1/File"
        }
      ],
      "created": "2024-09-09T17:13:58+02:00",
      "id": "https://web1.karlsruhe.de/oparl/bodies/0001/agendaitems/90009",
      "meeting": "https://web1.karlsruhe.de/oparl/bodies/0001/meetings/9914",
      "modified": "2025-03-03T13:33:42+01:00",
      "name": "Fragen und Anregungen der Einwohnerinnen und Einwohner",
      "number": "5",
      "order": 5,
      "public": true,
      "type": "https://schema.oparl.org/1.1/AgendaItem"
    },
    {
      "auxiliaryFile": [
        {
          "accessUrl": "https://web1.karlsruhe.de/oparl/bodies/0001/downloadfiles/a/00662578.pdf",
          "created": "2024-11-08T15:22:20+01:00",
          "date": "2024-11-08",
          "downloadUrl": "https://web1.karlsruhe.de/oparl/bodies/0001/downloadfiles/00662578.pdf",
          "fileName": "00662578.pdf",
          "id": "https://web1.karlsruhe.de/oparl/bodies/0001/files/662578",
          "mimeType": "application/pdf",
          "modified": "2025-04-30T10:38:52+02:00",
          "name": "2024-09-11_TOP_6_Protokollauszug",
          "type": "https://schema.oparl.org/1.1/File"
        }
      ],
      "consultation": "https://web1.karlsruhe.de/oparl/bodies/0001/consultations/32470",
      "created": "2024-09-09T17:06:28+02:00",
      "id": "https://web1.karlsruhe.de/oparl/bodies/0001/agendaitems/89992",
      "meeting": "https://web1.karlsruhe.de/oparl/bodies/0001/meetings/9914",
      "modified": "2025-03-03T13:33:42+01:00",
      "name": "Verfahren des Ortschaftsrates zum Vorschlag der Wahl des Ortsvorstehenden durch den Gemeinderat",
      "number": "6",
      "order": 6,
      "public": true,
      "type": "https://schema.oparl.org/1.1/AgendaItem"
    },
    {
      "auxiliaryFile": [
        {
          "accessUrl": "https://web1.karlsruhe.de/oparl/bodies/0001/downloadfiles/a/00662579.pdf",
          "created": "2024-11-08T15:22:32+01:00",
          "date": "2024-11-08",
          "downloadUrl": "https://web1.karlsruhe.de/oparl/bodies/0001/downloadfiles/00662579.pdf",
          "fileName": "00662579.pdf",
          "id": "https://web1.karlsruhe.de/oparl/bodies/0001/files/662579",
          "mimeType": "application/pdf",
          "modified": "2025-04-30T10:38:52+02:00",
          "name": "2024-09-11_TOP_7_Protokollauszug",
          "type": "https://schema.oparl.org/1.1/File"
        }
      ],
      "consultation": "https://web1.karlsruhe.de/oparl/bodies/0001/consultations/32566",
      "created": "2024-09-09T17:06:28+02:00",
      "id": "https://web1.karlsruhe.de/oparl/bodies/0001/agendaitems/89987",
      "meeting": "https://web1.karlsruhe.de/oparl/bodies/0001/meetings/9914",
      "modified": "2025-03-03T13:33:42+01:00",
      "name": "Schriftzug Herbert-Schweizer-Haus Begegnungsstätte Grötzingen",
      "number": "7",
      "order": 7,
      "public": true,
      "type": "https://schema.oparl.org/1.1/AgendaItem"
    },
    {
      "auxiliaryFile": [
        {
          "accessUrl": "https://web1.karlsruhe.de/oparl/bodies/0001/downloadfiles/a/00662580.pdf",
          "created": "2024-11-08T15:22:43+01:00",
          "date": "2024-11-08",
          "downloadUrl": "https://web1.karlsruhe.de/oparl/bodies/0001/downloadfiles/00662580.pdf",
          "fileName": "00662580.pdf",
          "id": "https://web1.karlsruhe.de/oparl/bodies/0001/files/662580",
          "mimeType": "application/pdf",
          "modified": "2025-04-30T10:38:52+02:00",
          "name": "2024-09-11_TOP_8_Protokollauszug",
          "type": "https://schema.oparl.org/1.1/File"
        }
      ],
      "consultation": "https://web1.karlsruhe.de/oparl/bodies/0001/consultations/32565",
      "created": "2024-09-09T17:06:28+02:00",
      "id": "https://web1.karlsruhe.de/oparl/bodies/0001/agendaitems/89993",
      "meeting": "https://web1.karlsruhe.de/oparl/bodies/0001/meetings/9914",
      "modified": "2025-03-03T13:33:42+01:00",
      "name": "Anhörung Planfeststellungsverfahren B293, Ortsumgehung Berghausen",
      "number": "8",
      "order": 8,
      "public": true,
      "type": "https://schema.oparl.org/1.1/AgendaItem"
    },
    {
      "auxiliaryFile": [
        {
          "accessUrl": "https://web1.karlsruhe.de/oparl/bodies/0001/downloadfiles/a/00662581.pdf",
          "created": "2024-11-08T15:22:55+01:00",
          "date": "2024-11-08",
          "downloadUrl": "https://web1.karlsruhe.de/oparl/bodies/0001/downloadfiles/00662581.pdf",
          "fileName": "00662581.pdf",
          "id": "https://web1.karlsruhe.de/oparl/bodies/0001/files/662581",
          "mimeType": "application/pdf",
          "modified": "2025-04-30T10:38:52+02:00",
          "name": "2024-09-11_TOP_9_Protokollauszug",
          "type": "https://schema.oparl.org/1.1/File"
        }
      ],
      "consultation": "https://web1.karlsruhe.de/oparl/bodies/0001/consultations/32778",
      "created": "2024-09-09T17:06:28+02:00",
      "id": "https://web1.karlsruhe.de/oparl/bodies/0001/agendaitems/90001",
      "meeting": "https://web1.karlsruhe.de/oparl/bodies/0001/meetings/9914",
      "modified": "2025-03-03T13:33:42+01:00",
      "name": "Ergänzte Stellungnahme zum Änderungsantrag der CDU vom 15.07.2024 zur Anpassung der Nutzungsentgelte Herbert-Schweizer-Haus Begegnungsstätte Grötzingen",
      "number": "9",
      "order": 9,
      "public": true,
      "type": "https://schema.oparl.org/1.1/AgendaItem"
    },
    {
      "created": "2024-09-09T17:13:27+02:00",
      "id": "https://web1.karlsruhe.de/oparl/bodies/0001/agendaitems/90008",
      "meeting": "https://web1.karlsruhe.de/oparl/bodies/0001/meetings/9914",
      "modified": "2025-03-03T13:33:42+01:00",
      "name": "Parkplätze Ortsmitte",
      "number": "10",
      "order": 10,
      "public": true,
      "type": "https://schema.oparl.org/1.1/AgendaItem"
    },
    {
      "created": "2024-09-09T17:16:18+02:00",
      "id": "https://web1.karlsruhe.de/oparl/bodies/0001/agendaitems/90010",
      "meeting": "https://web1.karlsruhe.de/oparl/bodies/0001/meetings/9914",
      "modified": "2025-03-03T13:33:42+01:00",
      "name": "Bauanträge",
      "number": "11",
      "order": 11,
      "public": true,
      "type": "https://schema.oparl.org/1.1/AgendaItem"
    },
    {
      "auxiliaryFile": [
        {
          "accessUrl": "https://web1.karlsruhe.de/oparl/bodies/0001/downloadfiles/a/00662582.pdf",
          "created": "2024-11-08T15:23:19+01:00",
          "date": "2024-11-08",
          "downloadUrl": "https://web1.karlsruhe.de/oparl/bodies/0001/downloadfiles/00662582.pdf",
          "fileName": "00662582.pdf",
          "id": "https://web1.karlsruhe.de/oparl/bodies/0001/files/662582",
          "mimeType": "application/pdf",
          "modified": "2025-04-30T10:38:52+02:00",
          "name": "2024-09-11_TOP_11.1_Protokollauszug",
          "type": "https://schema.oparl.org/1.1/File"
        }
      ],
      "consultation": "https://web1.karlsruhe.de/oparl/bodies/0001/consultations/32753",
      "created": "2024-09-09T17:06:28+02:00",
      "id": "https://web1.karlsruhe.de/oparl/bodies/0001/agendaitems/89998",
      "meeting": "https://web1.karlsruhe.de/oparl/bodies/0001/meetings/9914",
      "modified": "2025-03-03T13:33:42+01:00",
      "name": "Nutzungsänderung der Lagerhalle in offene Abstellhalle",
      "number": "11.1",
      "order": 12,
      "public": true,
      "type": "https://schema.oparl.org/1.1/AgendaItem"
    },
    {
      "auxiliaryFile": [
        {
          "accessUrl": "https://web1.karlsruhe.de/oparl/bodies/0001/downloadfiles/a/00662583.pdf",
          "created": "2024-11-08T15:23:30+01:00",
          "date": "2024-11-08",
          "downloadUrl": "https://web1.karlsruhe.de/oparl/bodies/0001/downloadfiles/00662583.pdf",
          "fileName": "00662583.pdf",
          "id": "https://web1.karlsruhe.de/oparl/bodies/0001/files/662583",
          "mimeType": "application/pdf",
          "modified": "2025-04-30T10:38:52+02:00",
          "name": "2024-09-11_TOP_11.2_Protokollauszug",
          "type": "https://schema.oparl.org/1.1/File"
        }
      ],
      "consultation": "https://web1.karlsruhe.de/oparl/bodies/0001/consultations/32762",
      "created": "2024-09-09T17:06:28+02:00",
      "id": "https://web1.karlsruhe.de/oparl/bodies/0001/agendaitems/90000",
      "meeting": "https://web1.karlsruhe.de/oparl/bodies/0001/meetings/9914",
      "modified": "2025-03-03T13:33:42+01:00",
      "name": "Bruchwaldstr. 70 - Aufstellen eines Containers zur Ausgabe von Getränken",
      "number": "11.2",
      "order": 13,
      "public": true,
      "type": "https://schema.oparl.org/1.1/AgendaItem"
    },
    {
      "auxiliaryFile": [
        {
          "accessUrl": "https://web1.karlsruhe.de/oparl/bodies/0001/downloadfiles/a/00662584.pdf",
          "created": "2024-11-08T15:23:41+01:00",
          "date": "2024-11-08",
          "downloadUrl": "https://web1.karlsruhe.de/oparl/bodies/0001/downloadfiles/00662584.pdf",
          "fileName": "00662584.pdf",
          "id": "https://web1.karlsruhe.de/oparl/bodies/0001/files/662584",
          "mimeType": "application/pdf",
          "modified": "2025-04-30T10:38:52+02:00",
          "name": "2024-09-11_TOP_11.3_Protokollauszug",
          "type": "https://schema.oparl.org/1.1/File"
        }
      ],
      "consultation": "https://web1.karlsruhe.de/oparl/bodies/0001/consultations/32754",
      "created": "2024-09-09T17:06:28+02:00",
      "id": "https://web1.karlsruhe.de/oparl/bodies/0001/agendaitems/89999",
      "meeting": "https://web1.karlsruhe.de/oparl/bodies/0001/meetings/9914",
      "modified": "2025-03-03T13:33:42+01:00",
      "name": "Im Sonnental 15 Errichtung eines Anbaus",
      "number": "11.3",
      "order": 14,
      "public": true,
      "type": "https://schema.oparl.org/1.1/AgendaItem"
    },
    {
      "auxiliaryFile": [
        {
          "accessUrl": "https://web1.karlsruhe.de/oparl/bodies/0001/downloadfiles/a/00662585.pdf",
          "created": "2024-11-08T15:24:25+01:00",
          "date": "2024-11-08",
          "downloadUrl": "https://web1.karlsruhe.de/oparl/bodies/0001/downloadfiles/00662585.pdf",
          "fileName": "00662585.pdf",
          "id": "https://web1.karlsruhe.de/oparl/bodies/0001/files/662585",
          "mimeType": "application/pdf",
          "modified": "2025-04-30T10:38:52+02:00",
          "name": "2024-11-09_TOP_12_Protokollauszug",
          "type": "https://schema.oparl.org/1.1/File"
        }
      ],
      "created": "2024-09-09T17:19:47+02:00",
      "id": "https://web1.karlsruhe.de/oparl/bodies/0001/agendaitems/90011",
      "meeting": "https://web1.karlsruhe.de/oparl/bodies/0001/meetings/9914",
      "modified": "2025-03-03T13:33:42+01:00",
      "name": "Mitteilungen der Ortsverwaltung",
      "number": "12",
      "order": 15,
      "public": true,
      "type": "https://schema.oparl.org/1.1/AgendaItem"
    },
    {
      "consultation": "https://web1.karlsruhe.de/oparl/bodies/0001/consultations/32739",
      "created": "2024-09-09T17:06:28+02:00",
      "id": "https://web1.karlsruhe.de/oparl/bodies/0001/agendaitems/89996",
      "meeting": "https://web1.karlsruhe.de/oparl/bodies/0001/meetings/9914",
      "modified": "2025-03-03T13:33:42+01:00",
      "name": "Verlegung des Wahllokals 020-21 in das Herbert-Schweizer-Haus Begegnungsstätte Grötzingen",
      "number": "12.1",
      "order": 16,
      "public": true,
      "type": "https://schema.oparl.org/1.1/AgendaItem"
    },
    {
      "consultation": "https://web1.karlsruhe.de/oparl/bodies/0001/consultations/32748",
      "created": "2024-09-09T17:06:28+02:00",
      "id": "https://web1.karlsruhe.de/oparl/bodies/0001/agendaitems/89997",
      "meeting": "https://web1.karlsruhe.de/oparl/bodies/0001/meetings/9914",
      "modified": "2025-03-03T13:33:42+01:00",
      "name": "Bedarfsprognose Kita-Plätze in Grötzingen",
      "number": "12.2",
      "order": 17,
      "public": true,
      "type": "https://schema.oparl.org/1.1/AgendaItem"
    }
  ],
  "auxiliaryFile": [
    {
      "accessUrl": "https://web1.karlsruhe.de/oparl/bodies/0001/downloadfiles/a/00662589.pdf",
      "created": "2024-11-08T15:25:18+01:00",
      "date": "2024-11-08",
      "downloadUrl": "https://web1.karlsruhe.de/oparl/bodies/0001/downloadfiles/00662589.pdf",
      "fileName": "00662589.pdf",
      "id": "https://web1.karlsruhe.de/oparl/bodies/0001/files/662589",
      "mimeType": "application/pdf",
      "modified": "2025-04-30T10:38:52+02:00",
      "name": "Protokoll öffentlich",
      "type": "https://schema.oparl.org/1.1/File"
    }
  ],
  "created": "2024-02-26T11:06:40+01:00",
  "end": "2024-09-11T21:00:00+02:00",
  "id": "https://web1.karlsruhe.de/oparl/bodies/0001/meetings/9914",
  "invitation": {
    "accessUrl": "https://web1.karlsruhe.de/oparl/bodies/0001/downloadfiles/a/00660521.pdf",
    "created": "2024-08-29T16:54:48+02:00",
    "date": "2024-09-09",
    "downloadUrl": "https://web1.karlsruhe.de/oparl/bodies/0001/downloadfiles/00660521.pdf",
    "fileName": "00660521.pdf",
    "id": "https://web1.karlsruhe.de/oparl/bodies/0001/files/660521",
    "mimeType": "application/pdf",
    "modified": "2025-04-30T10:38:52+02:00",
    "name": "Tagesordnung (öffentlich) Ausschuss/Ortschaftsrat",
    "type": "https://schema.oparl.org/1.1/File"
  },
  "location": {
    "created": "2024-02-26T11:06:40+01:00",
    "description": "Herbert-Schweizer-Haus Begegnungsstätte Grötzingen, Niddastraße 9, 76229 Karlsruhe",
    "id": "https://web1.karlsruhe.de/oparl/bodies/0001/locations/si/9914",
    "modified": "2025-04-30T10:38:52+02:00",
    "type": "https://schema.oparl.org/1.1/Location"
  },
  "modified": "2025-04-30T10:38:52+02:00",
  "name": "Ortschaftsrat Grötzingen (öffentlich/nicht öffentlich) - konstituierende Sitzung",
  "organization": [
    "https://web1.karlsruhe.de/oparl/bodies/0001/organizations/gr/33695"
  ],
  "start": "2024-09-11T19:30:00+02:00",
  "type": "https://schema.oparl.org/1.1/Meeting"
}
